HISTORY.txt
LICENSE
MANIFEST.in
README.md
pyproject.toml
rcsb/__init__.py
rcsb.utils.targets.egg-info/PKG-INFO
rcsb.utils.targets.egg-info/SOURCES.txt
rcsb.utils.targets.egg-info/dependency_links.txt
rcsb.utils.targets.egg-info/requires.txt
rcsb.utils.targets.egg-info/top_level.txt
rcsb/utils/__init__.py
rcsb/utils/targets/CARDTargetAnnotationProvider.py
rcsb/utils/targets/CARDTargetFeatureProvider.py
rcsb/utils/targets/CARDTargetOntologyProvider.py
rcsb/utils/targets/CARDTargetProvider.py
rcsb/utils/targets/ChEMBLTargetActivityProvider.py
rcsb/utils/targets/ChEMBLTargetCofactorProvider.py
rcsb/utils/targets/ChEMBLTargetMechanismProvider.py
rcsb/utils/targets/ChEMBLTargetProvider.py
rcsb/utils/targets/DrugBankTargetCofactorProvider.py
rcsb/utils/targets/DrugBankTargetProvider.py
rcsb/utils/targets/IMGTTargetFeatureProvider.py
rcsb/utils/targets/IMGTTargetProvider.py
rcsb/utils/targets/PharosTargetActivityProvider.py
rcsb/utils/targets/PharosTargetCofactorProvider.py
rcsb/utils/targets/PharosTargetProvider.py
rcsb/utils/targets/SAbDabTargetFeatureProvider.py
rcsb/utils/targets/SAbDabTargetProvider.py
rcsb/utils/targets/TargetCofactorDbProvider.py
rcsb/utils/targets/__init__.py