Metadata-Version: 2.4
Name: rcsb.utils.targets
Version: 0.88
Summary: RCSB Python Wrapper Module for Target Utilities
Author-email: John Westbrook <john.westbrook@rcsb.org>
License-Expression: Apache-2.0
Project-URL: Homepage, https://github.com/rcsb/py-rcsb_utils_targets
Classifier: Development Status :: 5 - Production/Stable
Classifier: Intended Audience :: Developers
Classifier: Natural Language :: English
Classifier: Programming Language :: Python
Classifier: Programming Language :: Python :: 3
Classifier: Programming Language :: Python :: 3.13
Requires-Python: >=3.9
License-File: LICENSE
Requires-Dist: rcsb.db>=1.809
Requires-Dist: rcsb.utils.io>=1.51
Requires-Dist: rcsb.utils.chemref>=0.93
Requires-Dist: rcsb.utils.config>=0.40
Requires-Dist: rcsb.utils.seq>=0.82
Requires-Dist: rcsb.utils.taxonomy>=0.43
Requires-Dist: rcsb.utils.multiproc>=0.20
Requires-Dist: chembl-webresource-client>=0.10.2
Provides-Extra: dev
Requires-Dist: check-manifest; extra == "dev"
Provides-Extra: tests
Requires-Dist: tox; extra == "tests"
Requires-Dist: pylint; extra == "tests"
Requires-Dist: black>=21.5b1; extra == "tests"
Requires-Dist: flake8; extra == "tests"
Requires-Dist: coverage; extra == "tests"
Dynamic: license-file
